{"genre:pop:lofi": 0.1, "mood:happy:chill": 0.1, "genre:pop:rock": 0.1, "mood:happy:intense": 0.1, "genre:pop:ambient": 0.1, "genre:pop:jazz": 0.1, "mood:happy:relaxed": 0.1, "genre:pop:synthwave": 0.1, "mood:happy:moody": 0.1, "mood:happy:focused": 0.1, "genre:pop:indie pop": 0.1, "genre:pop:electronic": 0.1, "genre:lofi:pop": 0.1, "mood:chill:happy": 0.1, "genre:lofi:rock": 0.1, "mood:chill:intense": 0.1, "genre:lofi:ambient": 0.1, "genre:lofi:jazz": 0.1, "mood:chill:relaxed": 0.1, "genre:lofi:synthwave": 0.1, "mood:chill:moody": 0.1, "mood:chill:focused": 0.1, "genre:lofi:indie pop": 0.1, "genre:lofi:electronic": 0.1, "mood:focused:happy": 0.1, "mood:focused:chill": 0.1, "mood:focused:intense": 0.1, "mood:focused:relaxed": 0.1, "mood:focused:moody": 0.1}